ostro/auth/__init__.py
ostro_auth-0.0.0a1.dist-info/METADATA
ostro_auth-0.0.0a1.dist-info/WHEEL
ostro_auth-0.0.0a1.dist-info/top_level.txt
ostro_auth-0.0.0a1.dist-info/RECORD
